ubo_gui/__init__.py
ubo_gui/_version.py
ubo_gui/constants.py
ubo_gui/logger.py
ubo_gui/utils.py
ubo_gui/animated_slider/__init__.py
ubo_gui/animated_slider/animated_slider.kv
ubo_gui/app/__init__.py
ubo_gui/app/app.kv
ubo_gui/assets/fonts/ArimoNerdFont-Bold.ttf
ubo_gui/assets/fonts/ArimoNerdFont-BoldItalic.ttf
ubo_gui/assets/fonts/ArimoNerdFont-Italic.ttf
ubo_gui/assets/fonts/ArimoNerdFont-Regular.ttf
"ubo_gui/assets/fonts/MaterialSymbolsOutlined[FILL,GRAD,opsz,wght].ttf"
ubo_gui/gauge/__init__.py
ubo_gui/gauge/gauge_widget.kv
ubo_gui/menu/__init__.py
ubo_gui/menu/_transitions.py
ubo_gui/menu/constants.py
ubo_gui/menu/menu.kv
ubo_gui/menu/menu_widget.py
ubo_gui/menu/stack_item.py
ubo_gui/menu/types.py
ubo_gui/menu/widgets/__init__.py
ubo_gui/menu/widgets/item_widget.kv
ubo_gui/menu/widgets/item_widget.py
ubo_gui/menu/widgets/menu_page_widget.kv
ubo_gui/menu/widgets/menu_page_widget.py
ubo_gui/notification/__init__.py
ubo_gui/notification/notification_widget.kv
ubo_gui/page/__init__.py
ubo_gui/progress_ring/__init__.py
ubo_gui/progress_ring/progress_ring_widget.kv
ubo_gui/prompt/__init__.py
ubo_gui/prompt/prompt_widget.kv
ubo_gui/qrcode/__init__.py
ubo_gui/spinner/__init__.py
ubo_gui/spinner/spinner_widget.kv
ubo_gui/volume/__init__.py
ubo_gui/volume/volume_widget.kv
ubo_gui-0.13.17.dist-info/METADATA
ubo_gui-0.13.17.dist-info/WHEEL
ubo_gui-0.13.17.dist-info/licenses/LICENSE
ubo_gui-0.13.17.dist-info/RECORD
