Metadata-Version: 2.4
Name: ubo-gui
Version: 0.13.17
Summary: GUI sdk for Ubo Pod
Project-URL: homepage, https://github.com/ubopod/ubo-gui/
Project-URL: repository, https://github.com/ubopod/ubo-gui/
Project-URL: documentation, https://github.com/ubopod/ubo-gui/
Project-URL: changelog, https://github.com/ubopod/ubo-gu//blob/main/CHANGELOG.md
Author-email: Sassan Haradji <me@sassanh.com>
Maintainer-email: Sassan Haradji <me@sassanh.com>
License: Apache-2.0
License-File: LICENSE
Keywords: components,kivy,ubo,widgets
Requires-Python: >=3.11
Requires-Dist: headless-kivy>=0.12.1
Requires-Dist: python-immutable>=1.0.2
Requires-Dist: qrcode>=7.4.2
